parrot_gpt/__init__.py
parrot_gpt/cli.py
parrot_gpt/exceptions.py
parrot_gpt/parrot_gpt.py
parrot_gpt/prompts.py
parrot_gpt-0.1.0.dist-info/AUTHORS.rst
parrot_gpt-0.1.0.dist-info/LICENSE
parrot_gpt-0.1.0.dist-info/METADATA
parrot_gpt-0.1.0.dist-info/WHEEL
parrot_gpt-0.1.0.dist-info/entry_points.txt
parrot_gpt-0.1.0.dist-info/top_level.txt
parrot_gpt-0.1.0.dist-info/RECORD
